Metadata-Version: 2.4
Name: iiif-validator-ng
Version: 0.1.0
Summary: IIIF Image API Validator NG
Author-email: Johannes Baiter <johannes.baiter@bsb-muenchen.de>, IIIF Contributors <simeon.warner@cornell.edu>
License: Apache-2.0
Project-URL: Homepage, https://github.com/dbmdz/image-validator-ng
Requires-Python: >=3.9
License-File: LICENSE.txt
Requires-Dist: pyvips>=3.0.0
Requires-Dist: rich>=14.1.0
Dynamic: license-file
